file_provenance_utils/__init__.py
file_provenance_utils/console_helper.py
file_provenance_utils/constants.py
file_provenance_utils/file_utils.py
file_provenance_utils/json_util.py
file_provenance_utils/plain_text_util.py
file_provenance_utils/system_caller.py
file_provenance_utils/xml_util.py
file_provenance_utils-0.1.1.dist-info/AUTHORS.rst
file_provenance_utils-0.1.1.dist-info/METADATA
file_provenance_utils-0.1.1.dist-info/WHEEL
file_provenance_utils-0.1.1.dist-info/entry_points.txt
file_provenance_utils-0.1.1.dist-info/top_level.txt
file_provenance_utils-0.1.1.dist-info/RECORD
