Metadata-Version: 2.2
Name: file_provenance_utils
Version: 0.1.1
Summary: Collection of functions for inserting provenance information to the output files.
Home-page: https://github.com/jai-python3/file-provenance-utils
Author: Jaideep Sundaram
Author-email: jai.python3@gmail.com
Keywords: file_provenance_utils
Classifier: Development Status :: 5 - Production/Stable
Classifier: Intended Audience :: Developers
Classifier: Natural Language :: English
Classifier: Programming Language :: Python :: 3.10
Requires-Python: >=3.10
License-File: AUTHORS.rst
Requires-Dist: Click>=7.0
Requires-Dist: PyYAML
Requires-Dist: Rich
Dynamic: author
Dynamic: author-email
Dynamic: classifier
Dynamic: description
Dynamic: description-content-type
Dynamic: home-page
Dynamic: keywords
Dynamic: requires-dist
Dynamic: requires-python
Dynamic: summary
